MANIFEST.in
README.md
setup.py
db_tqdm.egg-info/PKG-INFO
db_tqdm.egg-info/SOURCES.txt
db_tqdm.egg-info/dependency_links.txt
db_tqdm.egg-info/entry_points.txt
db_tqdm.egg-info/requires.txt
db_tqdm.egg-info/top_level.txt
dbtqdm/__init__.py
dbtqdm/consts.py
dbtqdm/db.py
dbtqdm/server.py
dbtqdm/utils.py
dbtqdm/args/__init__.py
dbtqdm/args/server.py
dbtqdm/mongo/__init__.py
dbtqdm/mongo/mongo.py
dbtqdm/static/__init__.py
dbtqdm/static/favicon.ico
dbtqdm/static/js/__init__.py
dbtqdm/static/js/barcontrol.js
dbtqdm/templates/__init__.py
dbtqdm/templates/bar.html
dbtqdm/templates/index.html