Metadata-Version: 2.1
Name: db-tqdm
Version: 1.1.3
Summary: A database tqdm process monitor with web user interface.
Home-page: https://github.com/jmgomezsoriano/db-tqdm
Author: José Manuel Gómez Soriano
Author-email: jmgomez.soriano@gmail.com
License: lGPLv3
Platform: UNKNOWN
Classifier: Programming Language :: Python :: 3
Classifier: License :: OSI Approved :: GNU General Public License v3 (GPLv3)
Classifier: Operating System :: OS Independent
Requires-Python: >=3.7
